btml/__about__.py
btml/__init__.py
btml/__main__.py
btml/btml_ast.py
btml/lexer.py
btml/parser.py
btml/server.py
btml/transpiler.py
btml-0.1.2.dist-info/METADATA
btml-0.1.2.dist-info/WHEEL
btml-0.1.2.dist-info/entry_points.txt
btml-0.1.2.dist-info/licenses/LICENSE.txt
btml-0.1.2.dist-info/RECORD
