Metadata-Version: 2.4
Name: btml
Version: 0.1.2
Summary: HTML but with curly brackets
Project-URL: Documentation, https://github.com/ImShyMike/btml#readme
Project-URL: Issues, https://github.com/ImShyMike/btml/issues
Project-URL: Source, https://github.com/ImShyMike/btml
Author-email: ShyMike <122023566+ImShyMike@users.noreply.github.com>
License-Expression: MIT
License-File: LICENSE.txt
Classifier: Programming Language :: Python
Classifier: Programming Language :: Python :: 3.10
Classifier: Programming Language :: Python :: 3.11
Classifier: Programming Language :: Python :: 3.12
Requires-Python: >=3.12
Requires-Dist: fastapi>=0.115.13
Requires-Dist: uvicorn>=0.34.3
